smartfarm_iot/__init__.py
smartfarm_iot/main.py
smartfarm_iot/modbus_reader.py
smartfarm_iot/mqtt_publisher.py
smartfarm_iot-0.0.14.dist-info/METADATA
smartfarm_iot-0.0.14.dist-info/WHEEL
smartfarm_iot-0.0.14.dist-info/entry_points.txt
smartfarm_iot-0.0.14.dist-info/top_level.txt
smartfarm_iot-0.0.14.dist-info/RECORD
