Metadata-Version: 2.1
Name: smartfarm-iot
Version: 0.0.14
Summary: A package for Smart Farm IoT data collection and publishing using Modbus TCP and MQTT
Home-page: http://www.doctor-ag.com/
Author: kimyuri
Author-email: rikim94@naver.com
License: UNKNOWN
Platform: UNKNOWN
Classifier: Programming Language :: Python :: 3
Classifier: License :: OSI Approved :: MIT License
Classifier: Operating System :: OS Independent
Requires-Python: >=3.6
Requires-Dist: paho-mqtt
Requires-Dist: pyModbusTCP
